conveyant/__init__.py
conveyant/compositors.py
conveyant/config.py
conveyant/containers.py
conveyant/emulate.py
conveyant/flows.py
conveyant/replicate.py
conveyant-0.0.3.dist-info/LICENSE
conveyant-0.0.3.dist-info/METADATA
conveyant-0.0.3.dist-info/WHEEL
conveyant-0.0.3.dist-info/top_level.txt
conveyant-0.0.3.dist-info/RECORD
