Metadata-Version: 2.1
Name: conveyant
Version: 0.0.3
Summary: Simple, lightweight functional flows
Author-email: Rastko Ciric <rastko@stanford.edu>
Maintainer-email: Rastko Ciric <rastko@stanford.edu>
License: Apache License
Project-URL: Homepage, https://github.com/hypercoil/conveyant
Classifier: Programming Language :: Python :: 3
Classifier: License :: OSI Approved :: Apache Software License
Classifier: Operating System :: POSIX :: Linux
Classifier: Operating System :: MacOS :: MacOS X
Requires-Python: >=3.10
License-File: LICENSE
Provides-Extra: dev
Requires-Dist: pytest ; extra == 'dev'
Requires-Dist: pytest-cov ; extra == 'dev'
Requires-Dist: coverage[toml] ; extra == 'dev'
Requires-Dist: ruff ; extra == 'dev'
